woven_gutter_gae-1.0.0-py3.7-nspkg.pth
gutter/client/__init__.py
gutter/client/compat.py
gutter/client/encoding.py
gutter/client/models.py
gutter/client/registry.py
gutter/client/signals.py
gutter/client/testutils.py
gutter/client/arguments/__init__.py
gutter/client/arguments/base.py
gutter/client/arguments/variables.py
gutter/client/operators/__init__.py
gutter/client/operators/comparable.py
gutter/client/operators/identity.py
gutter/client/operators/misc.py
gutter/client/operators/string.py
gutter/settings/__init__.py
gutter/settings/datastore_manager_settings.py
gutter/storage/__init__.py
gutter/storage/datastore_like_dict.py
woven_gutter_gae-1.0.0.dist-info/LICENSE
woven_gutter_gae-1.0.0.dist-info/METADATA
woven_gutter_gae-1.0.0.dist-info/WHEEL
woven_gutter_gae-1.0.0.dist-info/namespace_packages.txt
woven_gutter_gae-1.0.0.dist-info/top_level.txt
woven_gutter_gae-1.0.0.dist-info/RECORD
