Metadata-Version: 2.1
Name: woven-gutter-gae
Version: 1.0.0
Summary: Client to gutter feature switches backend, using GCP (Datastore and appengine)
Home-page: https://github.com/soulhave/woven-gutter-gae
Author: DISQUS, soulhave
Author-email: opensource@disqus.com, soulhave@yahoo.com.br
License: Apache License 2.0
Platform: UNKNOWN
Classifier: Development Status :: 5 - Production/Stable
Classifier: Intended Audience :: Developers
Classifier: Intended Audience :: System Administrators
Classifier: Operating System :: OS Independent
Classifier: Topic :: Software Development
Requires-Dist: durabledict (>=0.9.0)
Requires-Dist: jsonpickle
Requires-Dist: werkzeug
Requires-Dist: six
Requires-Dist: flask
Requires-Dist: flask-restplus
Requires-Dist: google-cloud-logging
Requires-Dist: google-cloud-datastore
Provides-Extra: test
Requires-Dist: nose ; extra == 'test'
Requires-Dist: exam ; extra == 'test'
Requires-Dist: mock ; extra == 'test'
Requires-Dist: django ; extra == 'test'
Requires-Dist: redis ; extra == 'test'
